uw_hrp/VERSION
uw_hrp/__init__.py
uw_hrp/dao.py
uw_hrp/models.py
uw_hrp/test.py
uw_hrp/resources/hrpws/file/hrp/v1/appointee/123456789.json
uw_hrp/resources/hrpws/file/hrp/v1/appointee/9136CCB8F66711D5BE060004AC494FFE.json
uw_hrp/resources/hrpws/file/hrp/v1/appointee/javerage.json
uw_hrp/resources/hrpws/file/hrp/v2/Worker.json_changed_since_2019_page_size_200_page_start_2
uw_hrp/resources/hrpws/file/hrp/v2/worker.json_changed_since_2019_page_size_200
uw_hrp/resources/hrpws/file/hrp/v2/worker.json_changed_since_2020_page_size_200
uw_hrp/resources/hrpws/file/hrp/v2/worker/10000000000000000000000000000015.json
uw_hrp/resources/hrpws/file/hrp/v2/worker/10000000000000000000000000000015.json_workerpositionstate_current_future
uw_hrp/resources/hrpws/file/hrp/v2/worker/100000015.json
uw_hrp/resources/hrpws/file/hrp/v2/worker/100000015.json_workerpositionstate_current_future
uw_hrp/resources/hrpws/file/hrp/v2/worker/chair.json
uw_hrp/resources/hrpws/file/hrp/v2/worker/faculty.json
uw_hrp/resources/hrpws/file/hrp/v2/worker/faculty.json_workerpositionstate_current_future
uw_hrp/resources/hrpws/file/hrp/v3/person.json_changed_since_date_2022-12-12_page_size_200
uw_hrp/resources/hrpws/file/hrp/v3/person/000000005.json
uw_hrp/resources/hrpws/file/hrp/v3/person/9136CCB8F66711D5BE060004AC494FFE.json
uw_hrp/resources/hrpws/file/hrp/v3/person/faculty.json
uw_hrp/resources/hrpws/file/hrp/v3/person/faculty.json_future_worker_true
uw_hrp/tests/__init__.py
uw_hrp/tests/test_dao.py
uw_hrp/tests/test_hrp.py
uw_hrp/tests/test_models.py
uw_hrp/util/__init__.py
uw_restclients_hrp-1.3.5.dist-info/licenses/LICENSE
uw_restclients_hrp-1.3.5.dist-info/METADATA
uw_restclients_hrp-1.3.5.dist-info/WHEEL
uw_restclients_hrp-1.3.5.dist-info/top_level.txt
uw_restclients_hrp-1.3.5.dist-info/RECORD
